newspaper/__init__.py
newspaper/__main__.py
newspaper/api.py
newspaper/article.py
newspaper/cleaners.py
newspaper/cli.py
newspaper/configuration.py
newspaper/exceptions.py
newspaper/languages.py
newspaper/mthreading.py
newspaper/network.py
newspaper/nlp.py
newspaper/outputformatters.py
newspaper/parsers.py
newspaper/settings.py
newspaper/source.py
newspaper/text.py
newspaper/urls.py
newspaper/version.py
newspaper/extractors/__init__.py
newspaper/extractors/articlebody_extractor.py
newspaper/extractors/authors_extractor.py
newspaper/extractors/categories_extractor.py
newspaper/extractors/content_extractor.py
newspaper/extractors/defines.py
newspaper/extractors/image_extractor.py
newspaper/extractors/metadata_extractor.py
newspaper/extractors/pubdate_extractor.py
newspaper/extractors/title_extractor.py
newspaper/extractors/videos_extractor.py
newspaper/resources/misc/google_sources.txt
newspaper/resources/misc/popular_sources.txt
newspaper/resources/misc/useragents.txt
newspaper/resources/text/stopwords-ar.txt
newspaper/resources/text/stopwords-be.txt
newspaper/resources/text/stopwords-bg.txt
newspaper/resources/text/stopwords-da.txt
newspaper/resources/text/stopwords-de.txt
newspaper/resources/text/stopwords-el.txt
newspaper/resources/text/stopwords-en.txt
newspaper/resources/text/stopwords-es.txt
newspaper/resources/text/stopwords-et.txt
newspaper/resources/text/stopwords-fa.txt
newspaper/resources/text/stopwords-fi.txt
newspaper/resources/text/stopwords-fr.txt
newspaper/resources/text/stopwords-he.txt
newspaper/resources/text/stopwords-hi.txt
newspaper/resources/text/stopwords-hr.txt
newspaper/resources/text/stopwords-hu.txt
newspaper/resources/text/stopwords-id.txt
newspaper/resources/text/stopwords-it.txt
newspaper/resources/text/stopwords-ja.txt
newspaper/resources/text/stopwords-ko.txt
newspaper/resources/text/stopwords-lt.txt
newspaper/resources/text/stopwords-mk.txt
newspaper/resources/text/stopwords-nb.txt
newspaper/resources/text/stopwords-nl.txt
chaintech-1.0.0.dist-info/METADATA
chaintech-1.0.0.dist-info/WHEEL
chaintech-1.0.0.dist-info/top_level.txt
chaintech-1.0.0.dist-info/RECORD
