Metadata-Version: 2.1
Name: chaintech
Version: 1.0.0
Author: Chaintech
Requires-Dist: importlib-resources ==5.4.0 ; python_version >= "3.6" and python_version < "3.7"
Requires-Dist: importlib-metadata ==4.8.3 ; python_version >= "3.6" and python_version < "3.8"
Requires-Dist: typing-extensions ==4.1.1 ; python_version >= "3.6" and python_version < "3.8"
Requires-Dist: zipp ==3.6.0 ; python_version >= "3.6" and python_version < "3.8"
Requires-Dist: beautifulsoup4 ==4.12.2 ; python_version >= "3.6" and python_version < "4.0"
Requires-Dist: certifi ==2023.7.22 ; python_version >= "3.6" and python_version < "4.0"
Requires-Dist: charset-normalizer ==2.0.12 ; python_version >= "3.6" and python_version < "4.0"
Requires-Dist: click ==8.0.4 ; python_version >= "3.6" and python_version < "4.0"
Requires-Dist: feedfinder2 ==0.0.4 ; python_version >= "3.6" and python_version < "4.0"
Requires-Dist: feedparser ==6.0.10 ; python_version >= "3.6" and python_version < "4.0"
Requires-Dist: filelock ==3.4.1 ; python_version >= "3.6" and python_version < "4.0"
Requires-Dist: idna ==3.4 ; python_version >= "3.6" and python_version < "4.0"
Requires-Dist: jieba3k ==0.35.1 ; python_version >= "3.6" and python_version < "4.0"
Requires-Dist: joblib ==1.1.1 ; python_version >= "3.6" and python_version < "4.0"
Requires-Dist: lxml ==4.9.3 ; python_version >= "3.6" and python_version < "4.0"
Requires-Dist: nltk ==3.6.7 ; python_version >= "3.6" and python_version < "4.0"
Requires-Dist: pillow ==8.4.0 ; python_version >= "3.6" and python_version < "4.0"
Requires-Dist: pythainlp ==2.3.2 ; python_version >= "3.6" and python_version < "4.0"
Requires-Dist: python-crfsuite ==0.9.9 ; python_version >= "3.6" and python_version < "4.0"
Requires-Dist: python-dateutil ==2.8.2 ; python_version >= "3.6" and python_version < "4.0"
Requires-Dist: pyyaml ==6.0.1 ; python_version >= "3.6" and python_version < "4.0"
Requires-Dist: regex ==2023.8.8 ; python_version >= "3.6" and python_version < "4.0"
Requires-Dist: requests-file ==1.5.1 ; python_version >= "3.6" and python_version < "4.0"
Requires-Dist: requests ==2.27.1 ; python_version >= "3.6" and python_version < "4.0"
Requires-Dist: sgmllib3k ==1.0.0 ; python_version >= "3.6" and python_version < "4.0"
Requires-Dist: six ==1.16.0 ; python_version >= "3.6" and python_version < "4.0"
Requires-Dist: soupsieve ==2.3.2.post1 ; python_version >= "3.6" and python_version < "4.0"
Requires-Dist: tinydb ==4.7.0 ; python_version >= "3.6" and python_version < "4.0"
Requires-Dist: tinysegmenter ==0.3 ; python_version >= "3.6" and python_version < "4.0"
Requires-Dist: tldextract ==3.1.2 ; python_version >= "3.6" and python_version < "4.0"
Requires-Dist: tqdm ==4.64.1 ; python_version >= "3.6" and python_version < "4.0"
Requires-Dist: urllib3 ==1.26.18 ; python_version >= "3.6" and python_version < "4.0"
Requires-Dist: colorama ==0.4.5 ; python_version >= "3.6" and python_version < "4.0" and platform_system == "Windows"
